LICENSE.md
MANIFEST.in
README.rst
setup.py
django_pydash_app.egg-info/PKG-INFO
django_pydash_app.egg-info/SOURCES.txt
django_pydash_app.egg-info/dependency_links.txt
django_pydash_app.egg-info/top_level.txt
pydash/__init__.py
pydash/services.py
pydash/settings.py
pydash/urls.py
pydash/views.py
pydash/static/css/bootstrap-responsive.min.css
pydash/static/css/bootstrap.min.css
pydash/static/css/dashboard.css
pydash/static/css/font-awesome.css
pydash/static/css/fonts.css
pydash/static/css/signin.css
pydash/static/css/style.css
pydash/static/fonts/MTP_ySUJH_bn48VBG8sNSnhCUOGz7vYGh680lGh-uXM.woff
pydash/static/fonts/MTP_ySUJH_bn48VBG8sNSonF5uFdDttMLvmWuJdhhgs.ttf
pydash/static/fonts/PRmiXeptR36kaC0GEAetxi8cqLH4MEiSE0ROcU-qHOA.ttf
pydash/static/fonts/PRmiXeptR36kaC0GEAetxn5HxGBcBvicCpTp6spHfNo.woff
pydash/static/fonts/cJZKeOuBrn4kERxqtaUH3T8E0i7KZn-EPnyo3HZu7kw.woff
pydash/static/fonts/cJZKeOuBrn4kERxqtaUH3aCWcynf_cDxXwCLxiixG1c.ttf
pydash/static/fonts/fontawesome-webfont.eot
pydash/static/fonts/fontawesome-webfont.svg
pydash/static/fonts/fontawesome-webfont.ttf
pydash/static/fonts/fontawesome-webfont.woff
pydash/static/fonts/glyphicons-halflings-regular.eot
pydash/static/fonts/glyphicons-halflings-regular.svg
pydash/static/fonts/glyphicons-halflings-regular.ttf
pydash/static/fonts/glyphicons-halflings-regular.woff
pydash/static/fonts/xjAJXh38I15wypJXxuGMBobN6UDyHWBl620a-IRfuBk.woff
pydash/static/fonts/xjAJXh38I15wypJXxuGMBp0EAVxt0G0biEntp43Qt6E.ttf
pydash/static/img/asc.gif
pydash/static/img/bg.gif
pydash/static/img/desc.gif
pydash/static/img/favicon.ico
pydash/static/img/icons-sa7c41345d9.png
pydash/static/js/Chart.min.js
pydash/static/js/base.js
pydash/static/js/bootstrap-multiselect.js
pydash/static/js/bootstrap.js
pydash/static/js/bootstrap.min.js
pydash/static/js/dashboard.js
pydash/static/js/excanvas.js
pydash/static/js/jquery.dataTables.min.js
pydash/static/js/jquery.js
pydash/templates/base_auth.html
pydash/templates/login.html
pydash/templates/logout.html
pydash/templates/main.html